pymupdf4llm/__init__.py
pymupdf4llm/versions_file.py
pymupdf4llm/helpers/check_ocr.py
pymupdf4llm/helpers/document_layout.py
pymupdf4llm/helpers/get_text_lines.py
pymupdf4llm/helpers/multi_column.py
pymupdf4llm/helpers/progress.py
pymupdf4llm/helpers/pymupdf_rag.py
pymupdf4llm/helpers/utils.py
pymupdf4llm/llama/pdf_markdown_reader.py
pymupdf4llm-0.2.6.dist-info/licenses/LICENSE
pymupdf4llm-0.2.6.dist-info/METADATA
pymupdf4llm-0.2.6.dist-info/WHEEL
pymupdf4llm-0.2.6.dist-info/top_level.txt
pymupdf4llm-0.2.6.dist-info/RECORD
