Metadata-Version: 2.4
Name: pymupdf4llm
Version: 0.2.6
Summary: PyMuPDF Utilities for LLM/RAG
Home-page: https://github.com/pymupdf/RAG
Author: Artifex
Author-email: support@artifex.com
License: Dual Licensed - GNU AFFERO GPL 3.0 or Artifex Commercial License
Project-URL: Documentation, https://pymupdf.readthedocs.io/
Project-URL: Source, https://github.com/pymupdf/RAG/tree/main/pymupdf4llm/pymupdf4llm
Project-URL: Tracker, https://github.com/pymupdf/RAG/issues
Project-URL: Changelog, https://github.com/pymupdf/RAG/blob/main/CHANGES.md
Project-URL: License, https://github.com/pymupdf/RAG/blob/main/LICENSE
Classifier: Development Status :: 5 - Production/Stable
Classifier: Environment :: Console
Classifier: Intended Audience :: Developers
Classifier: Programming Language :: Python :: 3
Classifier: Topic :: Utilities
Requires-Python: >=3.10
License-File: LICENSE
Requires-Dist: pymupdf>=1.26.6
Requires-Dist: tabulate
Provides-Extra: ocr
Requires-Dist: opencv-python; extra == "ocr"
Provides-Extra: layout
Requires-Dist: pymupdf-layout>=1.26.6; extra == "layout"
Dynamic: author
Dynamic: author-email
Dynamic: classifier
Dynamic: description
Dynamic: description-content-type
Dynamic: home-page
Dynamic: license
Dynamic: license-file
Dynamic: project-url
Dynamic: provides-extra
Dynamic: requires-dist
Dynamic: requires-python
Dynamic: summary
